pasted_client/__init__.py
pasted_client/pasted.py
pasted_client-0.1.1.dist-info/LICENSE
pasted_client-0.1.1.dist-info/METADATA
pasted_client-0.1.1.dist-info/WHEEL
pasted_client-0.1.1.dist-info/entry_points.txt
pasted_client-0.1.1.dist-info/top_level.txt
pasted_client-0.1.1.dist-info/RECORD
