Metadata-Version: 2.1
Name: pasted-client
Version: 0.1.1
Summary: Pasted client. Paste files or STDIN to a raw object.
Home-page: http://github.com/cloudnull/pasted-client
Author: Kevin Carter
Author-email: kevin@cloudnull.com
License: UNKNOWN
Platform: UNKNOWN
Classifier: Development Status :: 5 - Production/Stable
Classifier: Intended Audience :: Information Technology
Classifier: Intended Audience :: System Administrators
Classifier: Intended Audience :: Developers
Classifier: Operating System :: OS Independent
Classifier: Programming Language :: Python :: 3.6
Classifier: Topic :: Utilities
Classifier: Topic :: Software Development :: Libraries :: Python Modules
Requires-Dist: requests
